indopy_cxd/__init__.py
indopy_cxd/main.py
IndoPy-1.0.0.dist-info/METADATA
IndoPy-1.0.0.dist-info/WHEEL
IndoPy-1.0.0.dist-info/top_level.txt
IndoPy-1.0.0.dist-info/RECORD
