Metadata-Version: 2.1
Name: IndoPy
Version: 1.0.0
Summary: IndoPy adalah Packages Module Python berbahasa Indonesia yang akan membantu mempermudah proses pembelajaran.
Home-page: https://github.com/codexderes/indopy
Author: Codex Deres
Author-email: codexderes@gmail.com
License: UNKNOWN
Keywords: python indonesia,indopy,python berbahasa indonesia
Platform: UNKNOWN
Classifier: Development Status :: 1 - Planning
Classifier: Intended Audience :: Developers
Classifier: Programming Language :: Python :: 3
Classifier: Operating System :: Unix
Classifier: Operating System :: Microsoft :: Windows
